docuseal/__init__.py
docuseal/_api.py
docuseal/_http.py
docuseal/_version.py
docuseal-1.0.8.dist-info/licenses/LICENSE
docuseal-1.0.8.dist-info/METADATA
docuseal-1.0.8.dist-info/WHEEL
docuseal-1.0.8.dist-info/top_level.txt
docuseal-1.0.8.dist-info/RECORD
