Metadata-Version: 2.4
Name: docuseal
Version: 1.0.8
Summary: DocuSeal Python API client
Home-page: https://github.com/docusealco/docuseal-python
Author: DocuSeal
Author-email: admin@docuseal.com
License: MIT
Project-URL: Bug Tracker, https://github.com/docusealco/docuseal-python/issues
Project-URL: Changes, https://github.com/docusealco/docuseal-python/blob/master/CHANGELOG.md
Project-URL: Documentation, https://www.docuseal.com/docs/api?lang=python
Project-URL: Source Code, https://github.com/docusealco/docuseal-python
Keywords: docuseal document signature
Classifier: Development Status :: 5 - Production/Stable
Classifier: Intended Audience :: Developers
Classifier: License :: OSI Approved :: MIT License
Classifier: Operating System :: OS Independent
Classifier: Programming Language :: Python
Classifier: Programming Language :: Python :: 3
Classifier: Programming Language :: Python :: 3 :: Only
Classifier: Programming Language :: Python :: 3.6
Classifier: Programming Language :: Python :: 3.7
Classifier: Programming Language :: Python :: 3.8
Classifier: Programming Language :: Python :: 3.9
Classifier: Programming Language :: Python :: 3.10
Classifier: Programming Language :: Python :: 3.11
Classifier: Programming Language :: Python :: 3.12
Classifier: Programming Language :: Python :: Implementation :: CPython
Classifier: Programming Language :: Python :: Implementation :: PyPy
Classifier: Topic :: Software Development :: Libraries :: Python Modules
Requires-Python: >=3.6
License-File: LICENSE
Dynamic: author
Dynamic: author-email
Dynamic: classifier
Dynamic: description
Dynamic: description-content-type
Dynamic: home-page
Dynamic: keywords
Dynamic: license
Dynamic: license-file
Dynamic: project-url
Dynamic: requires-python
Dynamic: summary
